learon/__init__.py
Learon-0.5.dist-info/METADATA
Learon-0.5.dist-info/WHEEL
Learon-0.5.dist-info/top_level.txt
Learon-0.5.dist-info/RECORD
