Metadata-Version: 2.1
Name: Learon
Version: 0.5
Summary: High Level Machine Learning
Home-page: UNKNOWN
Author: Daron Théo
Author-email: eclairbleu12@gmail.com
License: MIT
Platform: UNKNOWN
Requires-Dist: scikit-learn
